setup.cfg
setup.py
tornadoes_ext/__init__.py
tornadoes_ext/models.py
tornadoes_ext/serializer.py
tornadoes_ext.egg-info/PKG-INFO
tornadoes_ext.egg-info/SOURCES.txt
tornadoes_ext.egg-info/dependency_links.txt
tornadoes_ext.egg-info/requires.txt
tornadoes_ext.egg-info/top_level.txt
tornadoes_ext.egg-info/zip-safe
tornadoes_ext/tests/__init__.py
tornadoes_ext/tests/unit/__init__.py
tornadoes_ext/tests/unit/test_tornadoes.py