Metadata-Version: 1.1
Name: tornadoes-ext
Version: 3.2.0
Summary: A tornado-powered python library that provides asynchronous access to elasticsearch. Extends the tornadoes package.
Home-page: http://github.com/Matityahul/tornado-es-ext
Author: Matityahul
Author-email: lior.mati@gmail.com
License: MIT
Download-URL: http://github.com/Matityahul/tornado-es-ext
Platform: UNKNOWN
Classifier: Development Status :: 4 - Beta
Classifier: Intended Audience :: Developers
Classifier: License :: OSI Approved :: MIT License
Classifier: Natural Language :: English
Classifier: Operating System :: Unix
Classifier: Operating System :: OS Independent
Classifier: Programming Language :: Python :: 2.7
Classifier: Programming Language :: Python :: 3.4
Classifier: Programming Language :: Python :: Implementation :: PyPy
